compas_3gs/__init__.py
compas_3gs/activate.py
compas_3gs/install.py
compas_3gs/algorithms/__init__.py
compas_3gs/algorithms/arearisation.py
compas_3gs/algorithms/duality.py
compas_3gs/algorithms/egi.py
compas_3gs/algorithms/other.py
compas_3gs/algorithms/planarisation.py
compas_3gs/algorithms/reciprocation.py
compas_3gs/algorithms/unifieddiagram.py
compas_3gs/datastructures/__init__.py
compas_3gs/datastructures/mesh3gs.py
compas_3gs/datastructures/network3gs.py
compas_3gs/datastructures/volmesh3gs.py
compas_3gs/diagrams/__init__.py
compas_3gs/diagrams/cell.py
compas_3gs/diagrams/disjointed.py
compas_3gs/diagrams/egi.py
compas_3gs/diagrams/polyhedral.py
compas_3gs/operations/__init__.py
compas_3gs/operations/celloperations.py
compas_3gs/operations/volmeshoperations.py
compas_3gs/utilities/__init__.py
compas_3gs/utilities/geometry.py
compas_3gs/utilities/other.py
compas_3gs/utilities/topology.py
compas_3gs-0.6.0.dist-info/AUTHORS.md
compas_3gs-0.6.0.dist-info/LICENSE
compas_3gs-0.6.0.dist-info/METADATA
compas_3gs-0.6.0.dist-info/WHEEL
compas_3gs-0.6.0.dist-info/top_level.txt
compas_3gs-0.6.0.dist-info/RECORD
