Metadata-Version: 2.1
Name: compas-3gs
Version: 0.6.0
Summary: A COMPAS package for 3D Graphic Statics
Home-page: https://github.com/BlockResearchGroup/compas_3gs
Author: Juney Lee
Author-email: juney.lee@arch.ethz.ch
License: MIT
Keywords: architecture,engineering
Platform: UNKNOWN
Classifier: Development Status :: 4 - Beta
Classifier: Intended Audience :: Developers
Classifier: Topic :: Scientific/Engineering
Classifier: License :: OSI Approved :: MIT License
Classifier: Operating System :: Unix
Classifier: Operating System :: POSIX
Classifier: Operating System :: Microsoft :: Windows
Classifier: Programming Language :: Python
Classifier: Programming Language :: Python :: 2.7
Classifier: Programming Language :: Python :: 3
Classifier: Programming Language :: Python :: 3.4
Classifier: Programming Language :: Python :: 3.5
Classifier: Programming Language :: Python :: 3.6
Classifier: Programming Language :: Python :: 3.7
Classifier: Programming Language :: Python :: Implementation :: CPython
Requires-Python: >=2.7
License-File: LICENSE
License-File: AUTHORS.md
Requires-Dist: compas
Requires-Dist: compas-skeleton (>=1.1.0)
